dcap_qvl-0.3.8.dist-info/METADATA
dcap_qvl-0.3.8.dist-info/WHEEL
dcap_qvl/__init__.py
dcap_qvl/_dcap_qvl.abi3.so
dcap_qvl/_dcap_qvl.pyi
dcap_qvl-0.3.8.dist-info/RECORD
