Metadata-Version: 2.4
Name: dcap-qvl
Version: 0.3.8
Classifier: Development Status :: 4 - Beta
Classifier: Intended Audience :: Developers
Classifier: License :: OSI Approved :: MIT License
Classifier: Programming Language :: Python :: 3
Classifier: Programming Language :: Python :: 3.8
Classifier: Programming Language :: Python :: 3.9
Classifier: Programming Language :: Python :: 3.10
Classifier: Programming Language :: Python :: 3.11
Classifier: Programming Language :: Python :: 3.12
Classifier: Programming Language :: Rust
Classifier: Topic :: Security :: Cryptography
Classifier: Topic :: Software Development :: Libraries
Summary: Python bindings for DCAP (Data Center Attestation Primitives) quote verification library
Keywords: sgx,tdx,dcap,attestation,verification,cryptography
Author-email: Kevin Wang <wy721@qq.com>
License: MIT
Requires-Python: >=3.8
Project-URL: Homepage, https://github.com/Phala-Network/dcap-qvl
Project-URL: Repository, https://github.com/Phala-Network/dcap-qvl
Project-URL: Issues, https://github.com/Phala-Network/dcap-qvl/issues
